fetchfox_sdk/__init__.py
fetchfox_sdk/client.py
fetchfox_sdk/item.py
fetchfox_sdk/workflow.py
fetchfox_sdk_beta-0.3.0.dist-info/LICENSE
fetchfox_sdk_beta-0.3.0.dist-info/METADATA
fetchfox_sdk_beta-0.3.0.dist-info/WHEEL
fetchfox_sdk_beta-0.3.0.dist-info/top_level.txt
fetchfox_sdk_beta-0.3.0.dist-info/RECORD
