Metadata-Version: 2.1
Name: fetchfox-sdk-beta
Version: 0.3.0
Summary: Python SDK for the FetchFox API.
Author-email: Thomas Ferrell <thomas@fetchfoxai.com>
License: pending
Project-URL: Homepage, https://fetchfox.ai
Project-URL: Documentation, https://github.com/fetchfox/fetchfox-sdk-python/tree/main/documentation
Project-URL: Source, https://github.com/fetchfox/fetchfox-sdk-python
Classifier: Programming Language :: Python :: 3
Classifier: Operating System :: OS Independent
Requires-Python: >=3.8
License-File: LICENSE
Requires-Dist: requests>=2.22.0
Provides-Extra: dev
Requires-Dist: pytest>=8.3.4; extra == "dev"
Requires-Dist: responses>=0.25.6; extra == "dev"
